{
  "kind": "blogger#post",
  "id": "7092644821842882809",
  "blog": {
    "id": "6814099569890334194"
  },
  "published": "2025-10-13T15:26:00-07:00",
  "updated": "2025-10-13T15:51:10-07:00",
  "url": "http://www.jdcredvip.com.br/2025/10/credito-do-trabalhador-uso-simplificado.html",
  "selfLink": "https://www.googleapis.com/blogger/v3/blogs/6814099569890334194/posts/7092644821842882809",
  "title": "Crédito do Trabalhador: Uso Simplificado no eSocial (Doméstico, MEI e Segurado Especial)",
  "content": "<p>&nbsp;📌 Crédito do Trabalhador: Uso Simplificado no eSocial (Doméstico, MEI e Segurado Especial)</p><p><span>Nem todos os empregadores precisam seguir o fluxo completo do <b>Crédito do Trabalhador</b>.\nPara quem utiliza os <b>Módulos Simplificados do eSocial</b> – como <b>empregadores domésticos, MEI e segurados especiais</b> – o processo é mais prático e automático.</span></p><div></div><h2>🖥️ Como funciona no eSocial Simplificado</h2><ul><li><p><span>As parcelas dos empréstimos consignados são <b>incluídas automaticamente</b> nas folhas de pagamento, rescisões e guias de recolhimento (DAE).</span></p></li><li><p><span>O empregador <b>não precisa baixar arquivos</b> no Portal Emprega Brasil nem lançar manualmente no eSocial.</span></p></li><li><p><span>O sistema já gera os descontos e inclui os valores nas guias de pagamento.</span></p></li><li><p><span>No caso de <b>rescisões</b>, o desconto do consignado é gerado apenas para empregadores domésticos.</span></p></li><li><p><span>Para MEI e segurados especiais, situações rescisórias são tratadas via <b>FGTS Digital</b>.</span></p></li></ul><div></div><h2>⚠️ Pontos de atenção</h2><ul><li><p><span>Mesmo sendo automático, o empregador deve <b>conferir os valores</b> antes de encerrar a folha.</span></p></li><li><p><span>O desconto só pode ocorrer até o limite de <b>35% da remuneração disponível</b>.</span></p></li><li><p><span>Caso o trabalhador não tenha saldo suficiente, o sistema pode registrar desconto parcial.</span></p></li></ul><div></div><h2>✅ Vantagens do módulo simplificado</h2><ul><li><p><span>Menos etapas manuais.</span></p></li><li><p><span>Redução de erros de escrituração.</span></p></li><li><p><span>Integração direta com a guia DAE.</span></p></li><li><p><span>Mais agilidade para pequenos empregadores.</span></p></li></ul><div></div><h2>❓ Mini FAQ – Uso Simplificado no eSocial</h2><p><span><b>1. Quem pode usar o módulo simplificado?</b>  \nEmpregadores domésticos, MEI e segurados especiais.</span></p><p><span><b>2. Preciso baixar arquivos no Portal Emprega Brasil?</b>  \nNão. O sistema já inclui automaticamente os descontos.</span></p><p><span><b>3. O desconto aparece na guia DAE?</b>  \nSim, os valores de consignado são incluídos junto com os demais encargos.</span></p><p><span><b>4. E no caso de rescisão?</b>  \nO desconto é gerado apenas para empregadores domésticos.</span></p><p><span><b>5. Preciso lançar rubrica no eSocial?</b>  \nNão. O sistema já faz isso automaticamente no módulo simplificado.</span></p><div></div><h2>📲 Quer simplificar ainda mais a gestão da sua folha?</h2>\n\n<h2>📚 Série Crédito do Trabalhador – Guia Completo para Empregadores</h2>\n<p>Confira abaixo todos os artigos da série sobre o <b>Crédito do Trabalhador</b>. Clique no tema desejado para acessar o conteúdo completo:</p>\n\n<ol>\n  <li><a href=\"https://www.jdcredvip.com.br/2025/10/o-que-e-o-credito-do-trabalhador.html\">O que é o Crédito do Trabalhador</a></li>\n  <li><a href=\"https://www.jdcredvip.com.br/2025/10/credito-do-trabalhador-visao.html\">Visão Simplificada + Passo a passo</a></li>\n  <li><a href=\"https://www.jdcredvip.com.br/2025/10/credito-do-trabalhador-notificacao-via.html\">Notificação via DET</a></li>\n  <li><a href=\"https://www.jdcredvip.com.br/2025/10/credito-do-trabalhador-consulta-das.html\">Consulta das consignações (Portal Emprega Brasil e API)</a></li>\n  <li><a href=\"https://www.jdcredvip.com.br/2025/10/credito-do-trabalhador-retencao-na.html\">Retenção na folha e regras dos 35%</a></li>\n  <li><a href=\"https://www.jdcredvip.com.br/2025/10/credito-do-trabalhador-situacoes.html\">Situações Especiais (demissão, férias, falta de saldo, etc.)</a></li>\n  <li><a href=\"https://www.jdcredvip.com.br/2025/10/credito-do-trabalhador-situacoes.html\">Escrituração no eSocial (rubrica 9253)</a></li>\n  <li><a href=\"https://www.jdcredvip.com.br/2025/10/credito-do-trabalhador-geracao-de-guias.html\">Geração de guias do FGTS Digital</a></li>\n  <li><a href=\"https://www.jdcredvip.com.br/2025/10/credito-do-trabalhador-uso-simplificado.html\">Uso simplificado no eSocial (Doméstico, MEI e Segurado Especial)</a></li>\n  <li><a href=\"https://www.jdcredvip.com.br/2025/10/credito-do-trabalhador-importancia-da.html\">Importância da escrituração correta</a></li>\n  <li><a href=\"https://www.jdcredvip.com.br/2025/10/credito-do-trabalhador-outras-consultas.html\">Outras consultas e informações</a></li>\n  <li><a href=\"https://www.jdcredvip.com.br/2025/10/credito-do-trabalhador-principais.html\">Principais obrigações do empregador (resumo)</a></li>\n</ol>\n\n<hr />\n",
  "author": {
    "id": "13031877485644427697",
    "displayName": "J &amp; D EMPRÉSTIMOS CONSIGNADOS",
    "url": "https://www.blogger.com/profile/13031877485644427697",
    "image": {
      "url": "//1.bp.blogspot.com/-Lg-UXrUGQA8/Znr1jGIswpI/AAAAAAAAAG0/s8AEEqtKwecyH6Ui15OHvf2u-se8PS31wCK4BGAYYCw/s35/pincode_1009650947619775708.png"
    }
  },
  "replies": {
    "totalItems": "0",
    "selfLink": "https://www.googleapis.com/blogger/v3/blogs/6814099569890334194/posts/7092644821842882809/comments"
  },
  "labels": [
    "Crédito do Trabalhador",
    "Doméstico",
    "MEI",
    "Segurado Especial",
    "Uso Simplificado no eSocial"
  ],
  "etag": "\"dGltZXN0YW1wOiAxNzYwMzk1ODcwNTQxCm9mZnNldDogLTI1MjAwMDAwCg\""
}